erknextframegen-0.0.1.dist-info/licenses/LICENSE
erknextframegen-0.0.1.dist-info/licenses/LICENSE_Llama3
erknextframegen-0.0.1.dist-info/licenses/NOTICE
src/data_processing/__init__.py
src/data_processing/data_processing.py
src/generator/__init__.py
src/generator/generator.py
src/model/__init__.py
src/model/cli.py
src/model/model.py
src/rule_based_generator/__init__.py
src/rule_based_generator/cli.py
src/rule_based_generator/rule_based_generator.py
src/trainer/__init__.py
src/trainer/cli.py
src/trainer/trainer.py
src/transformations/__init__.py
src/transformations/transformations.py
src/utils/__init__.py
src/utils/utils.py
src/visualizer/__init__.py
src/visualizer/visualizer.py
erknextframegen-0.0.1.dist-info/METADATA
erknextframegen-0.0.1.dist-info/WHEEL
erknextframegen-0.0.1.dist-info/entry_points.txt
erknextframegen-0.0.1.dist-info/top_level.txt
erknextframegen-0.0.1.dist-info/RECORD
