Metadata-Version: 2.4
Name: erknextframegen
Version: 0.0.1
Summary: Generator for biological experiments
Author-email: Adam Jaskuła <aj429467@gmail.com>, Michał Korniak <todo@email.com>, Michał Maszkowski <todo@email.com>, Zuz Mrozek? <todo@email.com>
License-Expression: MIT
Project-URL: Homepage, https://github.com/M-Korniak/ZPP
Project-URL: Bug-Tracker, https://github.com/M-Korniak/ZPP/issues
Classifier: Programming Language :: Python :: 3.10
Classifier: Intended Audience :: Science/Research
Requires-Python: >=3.10
License-File: LICENSE
License-File: LICENSE_Llama3
License-File: NOTICE
Requires-Dist: clearml~=1.10.1
Requires-Dist: gdown~=5.2.0
Requires-Dist: imageio~=2.37.0
Requires-Dist: matplotlib~=3.9
Requires-Dist: numpy~=2.1.3
Requires-Dist: pandas~=2.2.3
Requires-Dist: pytest~=8.1.0
Requires-Dist: scipy~=1.14.1
Requires-Dist: torch~=2.6.0
Requires-Dist: torchvision~=0.21.0
Requires-Dist: tqdm~=4.67.1
Dynamic: license-file
